MANIFEST.in
res_users.xml
setup.py
./__init__.py
./__openerp__.py
./res_users.py
./utils.py
./controllers/__init__.py
./controllers/main.py
i18n/ar.po
i18n/auth_openid.pot
i18n/cs.po
i18n/de.po
i18n/en_GB.po
i18n/es.po
i18n/es_CR.po
i18n/fi.po
i18n/fr.po
i18n/gu.po
i18n/hr.po
i18n/hu.po
i18n/it.po
i18n/ja.po
i18n/mk.po
i18n/mn.po
i18n/nb.po
i18n/nl.po
i18n/pl.po
i18n/pt.po
i18n/pt_BR.po
i18n/ro.po
i18n/ru.po
i18n/sk.po
i18n/sl.po
i18n/sr@latin.po
i18n/sv.po
i18n/tr.po
i18n/vi.po
i18n/zh_CN.po
openerp_auth_openid.egg-info/PKG-INFO
openerp_auth_openid.egg-info/SOURCES.txt
openerp_auth_openid.egg-info/dependency_links.txt
openerp_auth_openid.egg-info/requires.txt
openerp_auth_openid.egg-info/top_level.txt
static/src/img/aol.png
static/src/img/claimid.png
static/src/img/google.png
static/src/img/googleapps.gif
static/src/img/googlefav.png
static/src/img/launchpad.gif
static/src/img/launchpad.png
static/src/img/login-bg.gif
static/src/img/marketplace.gif
static/src/img/myopenid.png
static/src/img/openid.png
static/src/img/openid_16.png
static/src/img/textfield_key.png
static/src/img/verisign.png
static/src/img/yahoo.png
static/src/js/auth_openid.js
static/src/xml/auth_openid.xml